README.txt
setup.py
pygist/__init__.py
pygist/__main__.py
pygist/cli.py
pygist/config.py
pygist/core.py
pygist.egg-info/PKG-INFO
pygist.egg-info/SOURCES.txt
pygist.egg-info/dependency_links.txt
pygist.egg-info/entry_points.txt
pygist.egg-info/requires.txt
pygist.egg-info/top_level.txt