Metadata-Version: 1.0
Name: pygist
Version: 0.211
Summary: a simple cli for interacting with github gists
Home-page: https://github.com/Roasbeef/pygist
Author: Olaoluwa Osuntokun
Author-email: laolu32@gmail.com
License: MIT License
Platform: UNKNOWN
Classifier: Intended Audience :: Developers
Classifier: Natural Language :: English
Classifier: License :: OSI Approved :: MIT License
Classifier: Programming Language :: Python
Classifier: Programming Language :: Python :: 2.6
